rk_delta_SE/__init__.py
rk_delta_SE/main.py
rk_delta_SE-0.0.1.dist-info/METADATA
rk_delta_SE-0.0.1.dist-info/WHEEL
rk_delta_SE-0.0.1.dist-info/top_level.txt
rk_delta_SE-0.0.1.dist-info/RECORD
