Metadata-Version: 2.1
Name: rk_delta_SE
Version: 0.0.1
